cloudops_google_secretmanager/__init__.py
cloudops_google_secretmanager/secretmanager.py
cloudops_google_secretmanager-0.1.1.dist-info/WHEEL
cloudops_google_secretmanager-0.1.1.dist-info/METADATA
cloudops_google_secretmanager-0.1.1.dist-info/RECORD
