Metadata-Version: 2.1
Name: cloudops-google-secretmanager
Version: 0.1.1
Summary: 
Author: Manuel Castillo
Author-email: manucalop@gmail.com
Requires-Python: >=3.9,<4.0
Classifier: Programming Language :: Python :: 3
Classifier: Programming Language :: Python :: 3.10
Classifier: Programming Language :: Python :: 3.9
Requires-Dist: google-cloud-secret-manager (>=2.11.0,<3.0.0)
Requires-Dist: google-crc32c (>=1.3.0,<2.0.0)
